reader/__init__.py
reader/__main__.py
reader/config.txt
reader/feed.py
reader/viewer.py
realpy_feed-0.1.0.dist-info/entry_points.txt
realpy_feed-0.1.0.dist-info/WHEEL
realpy_feed-0.1.0.dist-info/METADATA
realpy_feed-0.1.0.dist-info/RECORD
