Metadata-Version: 2.1
Name: realpy-feed
Version: 0.1.0
Summary: Read the latest Real Python tutorials
Home-page: https://github.com/younger-1/realpy-feed
License: MIT
Author: Xavier Young
Author-email: 45989017+younger-1@users.noreply.github.com
Requires-Python: >=3.7,<4.0
Classifier: License :: OSI Approved :: MIT License
Classifier: Programming Language :: Python :: 3
Classifier: Programming Language :: Python :: 3.10
Classifier: Programming Language :: Python :: 3.7
Classifier: Programming Language :: Python :: 3.8
Classifier: Programming Language :: Python :: 3.9
Requires-Dist: feedparser (>=6.0.8,<7.0.0)
Requires-Dist: html2text (>=2020.1.16,<2021.0.0)
